makerbean/DataAnalysisBot.py
makerbean/ExcelBot.py
makerbean/PDFBot.py
makerbean/WebCrawlerBot.py
makerbean/WordBot.py
makerbean/__init__.py
makerbean/data.py
makerbean/stop_words.py
makerbean/utilities.py
makerbean-0.1.7.dist-info/LICENSE
makerbean-0.1.7.dist-info/METADATA
makerbean-0.1.7.dist-info/WHEEL
makerbean-0.1.7.dist-info/top_level.txt
makerbean-0.1.7.dist-info/RECORD
