Metadata-Version: 2.1
Name: makerbean
Version: 0.1.7
Summary: A small educational purpose package
Home-page: https://github.com/AndersonBY/python-makerbean
Author: MakerBi
Author-email: andersonby@163.com
License: UNKNOWN
Platform: UNKNOWN
Classifier: Programming Language :: Python :: 3
Classifier: License :: OSI Approved :: MIT License
Classifier: Operating System :: OS Independent
Requires-Python: >=3.6
Requires-Dist: openpyxl
Requires-Dist: requests
Requires-Dist: beautifulsoup4
Requires-Dist: lxml
Requires-Dist: jieba
Requires-Dist: pyecharts
Requires-Dist: pdfplumber
Requires-Dist: PyPDF2
Requires-Dist: python-docx
Requires-Dist: pandas
